rpi_hid/__init__.py
rpi_hid/device.py
rpi_hid/ducky.py
rpi_hid/keyboard.py
rpi_hid/keycodes.py
rpi_hid/utils.py
rpi_hid/webctl.py
rpi_hid/web/__init__.py
rpi_hid/web/app.py
rpi_hid/web/runner.py
rpi_hid/web/templates/ducky.html
rpi_hid/web/templates/python.html
rpi_hid-1.2.5.dist-info/licenses/LICENSE
rpi_hid-1.2.5.dist-info/METADATA
rpi_hid-1.2.5.dist-info/WHEEL
rpi_hid-1.2.5.dist-info/top_level.txt
rpi_hid-1.2.5.dist-info/RECORD
