Metadata-Version: 2.4
Name: rpi-hid
Version: 1.2.5
Summary: Raspberry Pi USB HID Keyboard + RubberDucky Interpreter
Home-page: https://github.com/AbhirupRudra/RPI-HID/
Author: Abhirup Rudra
Author-email: abhiruprudra@gmail.com
License: MIT
Classifier: Programming Language :: Python :: 3
Classifier: Operating System :: POSIX :: Linux
Classifier: License :: OSI Approved :: MIT License
Classifier: Topic :: System :: Hardware
Requires-Python: >=3.7
License-File: LICENSE
Dynamic: author
Dynamic: author-email
Dynamic: classifier
Dynamic: description
Dynamic: description-content-type
Dynamic: home-page
Dynamic: license
Dynamic: license-file
Dynamic: requires-python
Dynamic: summary
